bqml_xgboost_predictor/__init__.py
bqml_xgboost_predictor/main.py
bqml_xgboost_predictor/predictor.py
bqml_xgboost_predictor/predictor_test.py
bqml_xgboost_predictor-0.2.0.dist-info/LICENSE
bqml_xgboost_predictor-0.2.0.dist-info/METADATA
bqml_xgboost_predictor-0.2.0.dist-info/WHEEL
bqml_xgboost_predictor-0.2.0.dist-info/top_level.txt
bqml_xgboost_predictor-0.2.0.dist-info/RECORD
